cfn_guard_rs-0.3.3.dist-info/METADATA
cfn_guard_rs-0.3.3.dist-info/WHEEL
cfn_guard_rs/interface.py
cfn_guard_rs/py.typed
cfn_guard_rs/errors.py
cfn_guard_rs/api.py
cfn_guard_rs/__init__.py
cfn_guard_rs/cfn_guard_rs.cpython-38-aarch64-linux-gnu.so
cfn_guard_rs-0.3.3.dist-info/RECORD
