Metadata-Version: 2.1
Name: cfn_guard_rs
Version: 0.3.3
Classifier: Programming Language :: Rust
Classifier: Programming Language :: Python :: Implementation :: CPython
Classifier: Programming Language :: Python :: Implementation :: PyPy
Requires-Dist: pyyaml >=5.0.0
Requires-Python: >=3.7
